chessql/__init__.py
chessql/core/__init__.py
chessql/core/basenode.py
chessql/core/constants.py
chessql/core/cql.py
chessql/core/cqltypes.py
chessql/core/elements.py
chessql/core/filters.py
chessql/core/hhdb.py
chessql/core/keywords.py
chessql/core/options.py
chessql/core/parameters.py
chessql/core/parser.py
chessql/core/pattern.py
chessql/core/querycontainer.py
chessql/core/structure.py
chessql/core/tokenmap.py
chessql-3.0.1.dist-info/LICENCE
chessql-3.0.1.dist-info/METADATA
chessql-3.0.1.dist-info/WHEEL
chessql-3.0.1.dist-info/top_level.txt
chessql-3.0.1.dist-info/RECORD
