Metadata-Version: 2.1
Name: chessql
Version: 3.0.1
Summary: Chess Query Language (cql) parser.
Author-email: Roger Marsh <roger.marsh@solentware.co.uk>
License: Licence for cql package
Project-URL: Homepage, http://www.solentware.co.uk
Project-URL: Repository, https://github.com/RogerMarsh/chessql.git
Project-URL: Bug Tracker, https://github.com/RogerMarsh/chessql/issues
Classifier: License :: OSI Approved :: BSD License
Classifier: Programming Language :: Python :: 3.9
Classifier: Programming Language :: Python :: 3.10
Classifier: Programming Language :: Python :: 3.11
Classifier: Programming Language :: Python :: 3.12
Classifier: Operating System :: OS Independent
Classifier: Topic :: Games/Entertainment :: Board Games
Classifier: Intended Audience :: Developers
Classifier: Development Status :: 3 - Alpha
License-File: LICENCE
